setup.py
bin/sorbcrawler
sorbcrawler/__init__.py
sorbcrawler.egg-info/PKG-INFO
sorbcrawler.egg-info/SOURCES.txt
sorbcrawler.egg-info/dependency_links.txt
sorbcrawler.egg-info/not-zip-safe
sorbcrawler.egg-info/pbr.json
sorbcrawler.egg-info/requires.txt
sorbcrawler.egg-info/top_level.txt