Metadata-Version: 1.0
Name: sorbcrawler
Version: 1.01
Summary: Crawls through sorb forum threads, and returns the top 10 posters and their post count
Home-page: https://github.com/sid-eload/sorb-crawler
Author: sid-eload
Author-email: sideload3695@gmail.com
License: N/A
Keywords: sorb thread count post
Platform: UNKNOWN
